spice_client/__init__.py
spice_client/api_client.py
spice_client/api_response.py
spice_client/configuration.py
spice_client/exceptions.py
spice_client/py.typed
spice_client/rest.py
spice_client/api/__init__.py
spice_client/api/default_api.py
spice_client/helpers/__init__.py
spice_client/helpers/wrapper.py
spice_client/models/__init__.py
spice_client/models/asset.py
spice_client/models/asset_create.py
spice_client/models/asset_list.py
spice_client/models/asset_update.py
spice_client/models/dilution_summary.py
spice_client/models/experiment.py
spice_client/models/experiment_create.py
spice_client/models/experiment_list.py
spice_client/models/experiment_results_response.py
spice_client/models/experiment_results_summary_compact.py
spice_client/models/experiment_update.py
spice_client/models/location.py
spice_client/models/location_create.py
spice_client/models/location_list.py
spice_client/models/location_update.py
spice_client/models/nucleation_event.py
spice_client/models/nucleation_statistics.py
spice_client/models/probe.py
spice_client/models/probe_create.py
spice_client/models/probe_list.py
spice_client/models/probe_temperature_reading_with_metadata.py
spice_client/models/probe_update.py
spice_client/models/project.py
spice_client/models/project_create.py
spice_client/models/project_list.py
spice_client/models/project_update.py
spice_client/models/region.py
spice_client/models/region_create.py
spice_client/models/region_treatment_summary.py
spice_client/models/region_update.py
spice_client/models/sample.py
spice_client/models/sample_create.py
spice_client/models/sample_list.py
spice_client/models/sample_type.py
spice_client/models/sample_update.py
spice_client/models/temperature_data_with_probes.py
spice_client/models/tray.py
spice_client/models/tray_configuration.py
spice_client/models/tray_configuration_create.py
spice_client/models/tray_configuration_list.py
spice_client/models/tray_configuration_update.py
spice_client/models/tray_create.py
spice_client-0.1.3.dist-info/METADATA
spice_client-0.1.3.dist-info/WHEEL
spice_client-0.1.3.dist-info/RECORD
