Metadata-Version: 2.4
Name: spice-client
Version: 0.1.3
Summary: A Python client library for the SPICE ice nucleation API
Project-URL: Homepage, https://github.com/EERL-EPFL/spice-client
Project-URL: Repository, https://github.com/EERL-EPFL/spice-client.git
Project-URL: Documentation, https://github.com/EERL-EPFL/spice-client/blob/main/README.md
Project-URL: Issues, https://github.com/EERL-EPFL/spice-client/issues
Author-email: Evan Thomas <evan.thomas@epfl.ch>
Maintainer-email: Evan Thomas <evan.thomas@epfl.ch>
License: MIT
Keywords: climate science,environmental research,ice nucleation,laboratory data
Classifier: Development Status :: 4 - Beta
Classifier: Intended Audience :: Science/Research
Classifier: License :: OSI Approved :: MIT License
Classifier: Operating System :: OS Independent
Classifier: Programming Language :: Python :: 3
Classifier: Programming Language :: Python :: 3.12
Classifier: Topic :: Scientific/Engineering :: Atmospheric Science
Classifier: Topic :: Scientific/Engineering :: Chemistry
Classifier: Typing :: Typed
Requires-Python: >=3.12
Requires-Dist: geopandas>=1.1.1
Requires-Dist: jupyterlab>=4.4.6
Requires-Dist: pandas>=2.3.2
Requires-Dist: pydantic>=2.11.7
Requires-Dist: python-dateutil>=2.9.0.post0
Requires-Dist: python-keycloak>=5.8.1
Requires-Dist: typing-extensions>=4.15.0
Requires-Dist: urllib3>=2.5.0
